mqt_core_plugins_catalyst-1.0.0.dist-info/RECORD
mqt_core_plugins_catalyst-1.0.0.dist-info/WHEEL
mqt_core_plugins_catalyst-1.0.0.dist-info/entry_points.txt
mqt_core_plugins_catalyst-1.0.0.dist-info/METADATA
mqt_core_plugins_catalyst-1.0.0.dist-info/licenses/LICENSE.md
mqt/core/plugins/catalyst/_version.pyi
mqt/core/plugins/catalyst/_version.py
mqt/core/plugins/catalyst/device.py
mqt/core/plugins/catalyst/__init__.py
mqt/core/plugins/catalyst/mqt-core-plugins-catalyst.dylib
mqt/core/plugins/catalyst/plugin.py
