Metadata-Version: 2.4
Name: mqt-core-plugins-catalyst
Version: 1.0.0
Summary: An MLIR plugin for connecting MQT Core with Xanadu's Catalyst
Keywords: MQT,quantum-computing,design-automation,PennyLane,Catalyst,MLIR,plugin
Author-Email: Patrick Hopf <patrick.hopf@tum.de>, Yannick Stade <yannick.stade@tum.de>, Lukas Burgholzer <burgholzer@me.com>
License-Expression: MIT
License-File: LICENSE.md
Classifier: Development Status :: 4 - Beta
Classifier: Intended Audience :: Science/Research
Classifier: Natural Language :: English
Classifier: Operating System :: MacOS
Classifier: Operating System :: POSIX :: Linux
Classifier: Programming Language :: C++
Classifier: Programming Language :: Python
Classifier: Programming Language :: Python :: 3
Classifier: Programming Language :: Python :: 3 :: Only
Classifier: Programming Language :: Python :: 3.11
Classifier: Programming Language :: Python :: 3.12
Classifier: Programming Language :: Python :: 3.13
Classifier: Programming Language :: Python :: 3.14
Classifier: Topic :: Scientific/Engineering :: Electronic Design Automation (EDA)
Classifier: Typing :: Typed
Project-URL: Homepage, https://github.com/munich-quantum-toolkit/core-plugins-catalyst
Project-URL: Changelog, https://github.com/munich-quantum-toolkit/core-plugins-catalyst/blob/main/CHANGELOG.md
Project-URL: Documentation, https://mqt.readthedocs.io/projects/core-plugins-catalyst
Project-URL: Issues, https://github.com/munich-quantum-toolkit/core-plugins-catalyst/issues
Project-URL: Discussions, https://github.com/munich-quantum-toolkit/core-plugins-catalyst/discussions
Project-URL: PyPI, https://pypi.org/project/mqt-core-plugins-catalyst/
Requires-Python: >=3.11
Requires-Dist: pennylane-catalyst~=0.14.0
